chosic/__init__.py
chosic/chosic.py
chosic/enums/__init__.py
chosic/enums/genre.py
chosic/enums/mood.py
chosic-0.0.5.dist-info/METADATA
chosic-0.0.5.dist-info/WHEEL
chosic-0.0.5.dist-info/top_level.txt
chosic-0.0.5.dist-info/RECORD
