Metadata-Version: 2.1
Name: chosic
Version: 0.0.5
Summary: chosic
Home-page: https://github.com/kkristof200/py_chosic
Author: Kristof
License: UNKNOWN
Platform: UNKNOWN
Classifier: Programming Language :: Python :: 3
Classifier: License :: OSI Approved :: MIT License
Classifier: Operating System :: OS Independent
Requires-Python: >=3.5
Requires-Dist: ksimpleapi
Requires-Dist: beautifulsoup4
